.gitignore
AUTHORS
CHANGES
LICENSE
MANIFEST.in
README
README.rst
setup.cfg
setup.py
pixelinkds/__init__.py
pixelinkds/__main__.py
pixelinkds/converters.py
pixelinkds/reader.py
pixelinkds/types.py
pixelinkds.egg-info/PKG-INFO
pixelinkds.egg-info/SOURCES.txt
pixelinkds.egg-info/dependency_links.txt
pixelinkds.egg-info/top_level.txt
pixelinkds.egg-info/zip-safe