Metadata-Version: 1.1
Name: pixelinkds
Version: 0.1
Summary: PixeLINK Data Steam (PDS) Files in Python.
Home-page: https://github.com/hgrecco/pixelinkds
Author: Hernan E. Grecco
Author-email: hernan.grecco@gmail.com
License: BSD
Keywords: PixeLINK Data Stream PDS image movie
Platform: UNKNOWN
Classifier: Development Status :: 4 - Beta
Classifier: Intended Audience :: Developers
Classifier: Intended Audience :: Science/Research
Classifier: License :: OSI Approved :: BSD License
Classifier: Operating System :: MacOS :: MacOS X
Classifier: Operating System :: Microsoft :: Windows
Classifier: Operating System :: POSIX
Classifier: Programming Language :: Python
Classifier: Topic :: Scientific/Engineering
Classifier: Topic :: Software Development :: Libraries
Classifier: Programming Language :: Python :: 3.3
Classifier: Programming Language :: Python :: 3.4
Classifier: Programming Language :: Python :: 3.5
